{
  "ok": true,
  "version": 4,
  "guilds": [
    "반짝",
    "풍년순대국밥"
  ],
  "guild": "반짝 · 풍년순대국밥",
  "capturedDate": "2026-06-24",
  "comparisonMode": "weekly",
  "comparisonOffsetDays": -7,
  "comparisonTargetDate": "2026-06-17",
  "comparisonDates": {
    "반짝": null,
    "풍년순대국밥": null
  },
  "comparisonDateText": "반짝: 2026-06-17 데이터 없음 · 풍년순대국밥: 2026-06-17 데이터 없음",
  "summary": {
    "guildCount": 2,
    "memberCount": 54,
    "totalPowerValue": 824063634869669900,
    "totalTobeolValue": 1605535290000
  },
  "manualAppliedCount": 0,
  "guildSummaries": {
    "반짝": {
      "guildCount": 1,
      "memberCount": 28,
      "totalPowerValue": 822455195316580000,
      "totalTobeolValue": 1488326280000
    },
    "풍년순대국밥": {
      "guildCount": 1,
      "memberCount": 26,
      "totalPowerValue": 1608439553090000,
      "totalTobeolValue": 117209010000
    }
  },
  "members": [
    {
      "guild": "반짝",
      "rank": 1,
      "nickname": "냥쪼미",
      "job": "아크메이지(썬,콜)",
      "level": 120,
      "powerValue": 726821957486030000,
      "powerText": "72경 6821조 9574억 8602만",
      "previousPowerValue": null,
      "previousPowerText": null,
      "powerGrowthValue": null,
      "powerGrowthText": null,
      "powerGrowthRate": null,
      "tobeolValue": 884098710000,
      "tobeolText": "8840억 9871만",
      "previousTobeolValue": null,
      "previousTobeolText": null,
      "tobeolGrowthValue": null,
      "tobeolGrowthText": null,
      "tobeolGrowthRate": null
    },
    {
      "guild": "반짝",
      "rank": 2,
      "nickname": "느얭",
      "job": "팔라딘",
      "level": 115,
      "powerValue": 28724055713220000,
      "powerText": "2경 8724조 557억 1322만",
      "previousPowerValue": null,
      "previousPowerText": null,
      "powerGrowthValue": null,
      "powerGrowthText": null,
      "powerGrowthRate": null,
      "tobeolValue": 0,
      "tobeolText": "0",
      "previousTobeolValue": null,
      "previousTobeolText": null,
      "tobeolGrowthValue": null,
      "tobeolGrowthText": null,
      "tobeolGrowthRate": null
    },
    {
      "guild": "반짝",
      "rank": 3,
      "nickname": "복씽",
      "job": "섀도어",
      "level": 114,
      "powerValue": 14485827760680000,
      "powerText": "1경 4485조 8277억 6068만",
      "previousPowerValue": null,
      "previousPowerText": null,
      "powerGrowthValue": null,
      "powerGrowthText": null,
      "powerGrowthRate": null,
      "tobeolValue": 0,
      "tobeolText": "0",
      "previousTobeolValue": null,
      "previousTobeolText": null,
      "tobeolGrowthValue": null,
      "tobeolGrowthText": null,
      "tobeolGrowthRate": null
    },
    {
      "guild": "반짝",
      "rank": 4,
      "nickname": "아몬드롱롱",
      "job": "아크메이지(불,독)",
      "level": 117,
      "powerValue": 12679127163580000,
      "powerText": "1경 2679조 1271억 6358만",
      "previousPowerValue": null,
      "previousPowerText": null,
      "powerGrowthValue": null,
      "powerGrowthText": null,
      "powerGrowthRate": null,
      "tobeolValue": 0,
      "tobeolText": "0",
      "previousTobeolValue": null,
      "previousTobeolText": null,
      "tobeolGrowthValue": null,
      "tobeolGrowthText": null,
      "tobeolGrowthRate": null
    },
    {
      "guild": "반짝",
      "rank": 5,
      "nickname": "냥쪼me",
      "job": "신궁",
      "level": 113,
      "powerValue": 11909442619330000,
      "powerText": "1경 1909조 4426억 1933만",
      "previousPowerValue": null,
      "previousPowerText": null,
      "powerGrowthValue": null,
      "powerGrowthText": null,
      "powerGrowthRate": null,
      "tobeolValue": 159531640000,
      "tobeolText": "1595억 3164만",
      "previousTobeolValue": null,
      "previousTobeolText": null,
      "tobeolGrowthValue": null,
      "tobeolGrowthText": null,
      "tobeolGrowthRate": null
    },
    {
      "guild": "반짝",
      "rank": 6,
      "nickname": "봉지쑤시개",
      "job": "신궁",
      "level": 113,
      "powerValue": 7713094458680000,
      "powerText": "7713조 944억 5868만",
      "previousPowerValue": null,
      "previousPowerText": null,
      "powerGrowthValue": null,
      "powerGrowthText": null,
      "powerGrowthRate": null,
      "tobeolValue": 0,
      "tobeolText": "0",
      "previousTobeolValue": null,
      "previousTobeolText": null,
      "tobeolGrowthValue": null,
      "tobeolGrowthText": null,
      "tobeolGrowthRate": null
    },
    {
      "guild": "반짝",
      "rank": 7,
      "nickname": "득규",
      "job": "비숍",
      "level": 113,
      "powerValue": 5208217734990000,
      "powerText": "5208조 2177억 3499만",
      "previousPowerValue": null,
      "previousPowerText": null,
      "powerGrowthValue": null,
      "powerGrowthText": null,
      "powerGrowthRate": null,
      "tobeolValue": 129446890000,
      "tobeolText": "1294억 4689만",
      "previousTobeolValue": null,
      "previousTobeolText": null,
      "tobeolGrowthValue": null,
      "tobeolGrowthText": null,
      "tobeolGrowthRate": null
    },
    {
      "guild": "반짝",
      "rank": 8,
      "nickname": "인민펀치",
      "job": "섀도어",
      "level": 111,
      "powerValue": 4603761044330000,
      "powerText": "4603조 7610억 4433만",
      "previousPowerValue": null,
      "previousPowerText": null,
      "powerGrowthValue": null,
      "powerGrowthText": null,
      "powerGrowthRate": null,
      "tobeolValue": 19390700000,
      "tobeolText": "193억 9070만",
      "previousTobeolValue": null,
      "previousTobeolText": null,
      "tobeolGrowthValue": null,
      "tobeolGrowthText": null,
      "tobeolGrowthRate": null
    },
    {
      "guild": "반짝",
      "rank": 9,
      "nickname": "망동",
      "job": "다크나이트",
      "level": 111,
      "powerValue": 2040929661680000,
      "powerText": "2040조 9296억 6168만",
      "previousPowerValue": null,
      "previousPowerText": null,
      "powerGrowthValue": null,
      "powerGrowthText": null,
      "powerGrowthRate": null,
      "tobeolValue": 0,
      "tobeolText": "0",
      "previousTobeolValue": null,
      "previousTobeolText": null,
      "tobeolGrowthValue": null,
      "tobeolGrowthText": null,
      "tobeolGrowthRate": null
    },
    {
      "guild": "반짝",
      "rank": 10,
      "nickname": "밍또기",
      "job": "섀도어",
      "level": 111,
      "powerValue": 1723780822490000,
      "powerText": "1723조 7808억 2249만",
      "previousPowerValue": null,
      "previousPowerText": null,
      "powerGrowthValue": null,
      "powerGrowthText": null,
      "powerGrowthRate": null,
      "tobeolValue": 67533200000,
      "tobeolText": "675억 3320만",
      "previousTobeolValue": null,
      "previousTobeolText": null,
      "tobeolGrowthValue": null,
      "tobeolGrowthText": null,
      "tobeolGrowthRate": null
    },
    {
      "guild": "반짝",
      "rank": 11,
      "nickname": "욱진3",
      "job": "팔라딘",
      "level": 111,
      "powerValue": 1626461757760000,
      "powerText": "1626조 4617억 5776만",
      "previousPowerValue": null,
      "previousPowerText": null,
      "powerGrowthValue": null,
      "powerGrowthText": null,
      "powerGrowthRate": null,
      "tobeolValue": 67056270000,
      "tobeolText": "670억 5627만",
      "previousTobeolValue": null,
      "previousTobeolText": null,
      "tobeolGrowthValue": null,
      "tobeolGrowthText": null,
      "tobeolGrowthRate": null
    },
    {
      "guild": "반짝",
      "rank": 12,
      "nickname": "결하",
      "job": "비숍",
      "level": 110,
      "powerValue": 860052319950000,
      "powerText": "860조 523억 1995만",
      "previousPowerValue": null,
      "previousPowerText": null,
      "powerGrowthValue": null,
      "powerGrowthText": null,
      "powerGrowthRate": null,
      "tobeolValue": 36672840000,
      "tobeolText": "366억 7284만",
      "previousTobeolValue": null,
      "previousTobeolText": null,
      "tobeolGrowthValue": null,
      "tobeolGrowthText": null,
      "tobeolGrowthRate": null
    },
    {
      "guild": "반짝",
      "rank": 13,
      "nickname": "으웩",
      "job": "다크나이트",
      "level": 109,
      "powerValue": 529708940610000,
      "powerText": "529조 7089억 4061만",
      "previousPowerValue": null,
      "previousPowerText": null,
      "powerGrowthValue": null,
      "powerGrowthText": null,
      "powerGrowthRate": null,
      "tobeolValue": 0,
      "tobeolText": "0",
      "previousTobeolValue": null,
      "previousTobeolText": null,
      "tobeolGrowthValue": null,
      "tobeolGrowthText": null,
      "tobeolGrowthRate": null
    },
    {
      "guild": "반짝",
      "rank": 14,
      "nickname": "걀보",
      "job": "아크메이지(썬,콜)",
      "level": 108,
      "powerValue": 499663202340000,
      "powerText": "499조 6632억 234만",
      "previousPowerValue": null,
      "previousPowerText": null,
      "powerGrowthValue": null,
      "powerGrowthText": null,
      "powerGrowthRate": null,
      "tobeolValue": 0,
      "tobeolText": "0",
      "previousTobeolValue": null,
      "previousTobeolText": null,
      "tobeolGrowthValue": null,
      "tobeolGrowthText": null,
      "tobeolGrowthRate": null
    },
    {
      "guild": "반짝",
      "rank": 15,
      "nickname": "하깁s",
      "job": "다크나이트",
      "level": 107,
      "powerValue": 499077226320000,
      "powerText": "499조 772억 2632만",
      "previousPowerValue": null,
      "previousPowerText": null,
      "powerGrowthValue": null,
      "powerGrowthText": null,
      "powerGrowthRate": null,
      "tobeolValue": 10094770000,
      "tobeolText": "100억 9477만",
      "previousTobeolValue": null,
      "previousTobeolText": null,
      "tobeolGrowthValue": null,
      "tobeolGrowthText": null,
      "tobeolGrowthRate": null
    },
    {
      "guild": "반짝",
      "rank": 16,
      "nickname": "코푼",
      "job": "비숍",
      "level": 109,
      "powerValue": 495227440590000,
      "powerText": "495조 2274억 4059만",
      "previousPowerValue": null,
      "previousPowerText": null,
      "powerGrowthValue": null,
      "powerGrowthText": null,
      "powerGrowthRate": null,
      "tobeolValue": 29203080000,
      "tobeolText": "292억 308만",
      "previousTobeolValue": null,
      "previousTobeolText": null,
      "tobeolGrowthValue": null,
      "tobeolGrowthText": null,
      "tobeolGrowthRate": null
    },
    {
      "guild": "반짝",
      "rank": 17,
      "nickname": "빨풍",
      "job": "신궁",
      "level": 109,
      "powerValue": 434581416920000,
      "powerText": "434조 5814억 1692만",
      "previousPowerValue": null,
      "previousPowerText": null,
      "powerGrowthValue": null,
      "powerGrowthText": null,
      "powerGrowthRate": null,
      "tobeolValue": 0,
      "tobeolText": "0",
      "previousTobeolValue": null,
      "previousTobeolText": null,
      "tobeolGrowthValue": null,
      "tobeolGrowthText": null,
      "tobeolGrowthRate": null
    },
    {
      "guild": "반짝",
      "rank": 18,
      "nickname": "단소빌런",
      "job": "다크나이트",
      "level": 107,
      "powerValue": 204713583090000,
      "powerText": "204조 7135억 8309만",
      "previousPowerValue": null,
      "previousPowerText": null,
      "powerGrowthValue": null,
      "powerGrowthText": null,
      "powerGrowthRate": null,
      "tobeolValue": 0,
      "tobeolText": "0",
      "previousTobeolValue": null,
      "previousTobeolText": null,
      "tobeolGrowthValue": null,
      "tobeolGrowthText": null,
      "tobeolGrowthRate": null
    },
    {
      "guild": "반짝",
      "rank": 19,
      "nickname": "승호숍",
      "job": "비숍",
      "level": 107,
      "powerValue": 191035483490000,
      "powerText": "191조 354억 8349만",
      "previousPowerValue": null,
      "previousPowerText": null,
      "powerGrowthValue": null,
      "powerGrowthText": null,
      "powerGrowthRate": null,
      "tobeolValue": 11324350000,
      "tobeolText": "113억 2435만",
      "previousTobeolValue": null,
      "previousTobeolText": null,
      "tobeolGrowthValue": null,
      "tobeolGrowthText": null,
      "tobeolGrowthRate": null
    },
    {
      "guild": "반짝",
      "rank": 20,
      "nickname": "뜨거운밤",
      "job": "섀도어",
      "level": 107,
      "powerValue": 181965655010000,
      "powerText": "181조 9656억 5501만",
      "previousPowerValue": null,
      "previousPowerText": null,
      "powerGrowthValue": null,
      "powerGrowthText": null,
      "powerGrowthRate": null,
      "tobeolValue": 0,
      "tobeolText": "0",
      "previousTobeolValue": null,
      "previousTobeolText": null,
      "tobeolGrowthValue": null,
      "tobeolGrowthText": null,
      "tobeolGrowthRate": null
    },
    {
      "guild": "반짝",
      "rank": 21,
      "nickname": "복써",
      "job": "섀도어",
      "level": 106,
      "powerValue": 163918642240000,
      "powerText": "163조 9186억 4224만",
      "previousPowerValue": null,
      "previousPowerText": null,
      "powerGrowthValue": null,
      "powerGrowthText": null,
      "powerGrowthRate": null,
      "tobeolValue": 10564750000,
      "tobeolText": "105억 6475만",
      "previousTobeolValue": null,
      "previousTobeolText": null,
      "tobeolGrowthValue": null,
      "tobeolGrowthText": null,
      "tobeolGrowthRate": null
    },
    {
      "guild": "반짝",
      "rank": 22,
      "nickname": "밍츄핑",
      "job": "섀도어",
      "level": 106,
      "powerValue": 163612539530000,
      "powerText": "163조 6125억 3953만",
      "previousPowerValue": null,
      "previousPowerText": null,
      "powerGrowthValue": null,
      "powerGrowthText": null,
      "powerGrowthRate": null,
      "tobeolValue": 21596320000,
      "tobeolText": "215억 9632만",
      "previousTobeolValue": null,
      "previousTobeolText": null,
      "tobeolGrowthValue": null,
      "tobeolGrowthText": null,
      "tobeolGrowthRate": null
    },
    {
      "guild": "반짝",
      "rank": 23,
      "nickname": "바개몬",
      "job": "아크메이지(썬,콜)",
      "level": 107,
      "powerValue": 162131788000000,
      "powerText": "162조 1317억 8800만",
      "previousPowerValue": null,
      "previousPowerText": null,
      "powerGrowthValue": null,
      "powerGrowthText": null,
      "powerGrowthRate": null,
      "tobeolValue": 16867920000,
      "tobeolText": "168억 6792만",
      "previousTobeolValue": null,
      "previousTobeolText": null,
      "tobeolGrowthValue": null,
      "tobeolGrowthText": null,
      "tobeolGrowthRate": null
    },
    {
      "guild": "반짝",
      "rank": 24,
      "nickname": "쪼록",
      "job": "섀도어",
      "level": 107,
      "powerValue": 128509270450000,
      "powerText": "128조 5092억 7045만",
      "previousPowerValue": null,
      "previousPowerText": null,
      "powerGrowthValue": null,
      "powerGrowthText": null,
      "powerGrowthRate": null,
      "tobeolValue": 0,
      "tobeolText": "0",
      "previousTobeolValue": null,
      "previousTobeolText": null,
      "tobeolGrowthValue": null,
      "tobeolGrowthText": null,
      "tobeolGrowthRate": null
    },
    {
      "guild": "반짝",
      "rank": 25,
      "nickname": "갱미킴",
      "job": "다크나이트",
      "level": 106,
      "powerValue": 120276111970000,
      "powerText": "120조 2761억 1197만",
      "previousPowerValue": null,
      "previousPowerText": null,
      "powerGrowthValue": null,
      "powerGrowthText": null,
      "powerGrowthRate": null,
      "tobeolValue": 10421810000,
      "tobeolText": "104억 2181만",
      "previousTobeolValue": null,
      "previousTobeolText": null,
      "tobeolGrowthValue": null,
      "tobeolGrowthText": null,
      "tobeolGrowthRate": null
    },
    {
      "guild": "반짝",
      "rank": 26,
      "nickname": "왕오이",
      "job": "섀도어",
      "level": 106,
      "powerValue": 99804082380000,
      "powerText": "99조 8040억 8238만",
      "previousPowerValue": null,
      "previousPowerText": null,
      "powerGrowthValue": null,
      "powerGrowthText": null,
      "powerGrowthRate": null,
      "tobeolValue": 0,
      "tobeolText": "0",
      "previousTobeolValue": null,
      "previousTobeolText": null,
      "tobeolGrowthValue": null,
      "tobeolGrowthText": null,
      "tobeolGrowthRate": null
    },
    {
      "guild": "반짝",
      "rank": 27,
      "nickname": "랏뚜",
      "job": "히어로",
      "level": 106,
      "powerValue": 93831533250000,
      "powerText": "93조 8315억 3325만",
      "previousPowerValue": null,
      "previousPowerText": null,
      "powerGrowthValue": null,
      "powerGrowthText": null,
      "powerGrowthRate": null,
      "tobeolValue": 14523030000,
      "tobeolText": "145억 2303만",
      "previousTobeolValue": null,
      "previousTobeolText": null,
      "tobeolGrowthValue": null,
      "tobeolGrowthText": null,
      "tobeolGrowthRate": null
    },
    {
      "guild": "반짝",
      "rank": 28,
      "nickname": "보리쇼츄",
      "job": "섀도어",
      "level": 106,
      "powerValue": 90429857670000,
      "powerText": "90조 4298억 5767만",
      "previousPowerValue": null,
      "previousPowerText": null,
      "powerGrowthValue": null,
      "powerGrowthText": null,
      "powerGrowthRate": null,
      "tobeolValue": 0,
      "tobeolText": "0",
      "previousTobeolValue": null,
      "previousTobeolText": null,
      "tobeolGrowthValue": null,
      "tobeolGrowthText": null,
      "tobeolGrowthRate": null
    },
    {
      "guild": "풍년순대국밥",
      "rank": 1,
      "nickname": "더반",
      "job": "다크나이트",
      "level": 108,
      "powerValue": 284296397930000,
      "powerText": "284조 2963억 9793만",
      "previousPowerValue": null,
      "previousPowerText": null,
      "powerGrowthValue": null,
      "powerGrowthText": null,
      "powerGrowthRate": null,
      "tobeolValue": 14010270000,
      "tobeolText": "140억 1027만",
      "previousTobeolValue": null,
      "previousTobeolText": null,
      "tobeolGrowthValue": null,
      "tobeolGrowthText": null,
      "tobeolGrowthRate": null
    },
    {
      "guild": "풍년순대국밥",
      "rank": 2,
      "nickname": "윈썬콜",
      "job": "아크메이지(썬,콜)",
      "level": 106,
      "powerValue": 127828803040000,
      "powerText": "127조 8288억 304만",
      "previousPowerValue": null,
      "previousPowerText": null,
      "powerGrowthValue": null,
      "powerGrowthText": null,
      "powerGrowthRate": null,
      "tobeolValue": 11220150000,
      "tobeolText": "112억 2015만",
      "previousTobeolValue": null,
      "previousTobeolText": null,
      "tobeolGrowthValue": null,
      "tobeolGrowthText": null,
      "tobeolGrowthRate": null
    },
    {
      "guild": "풍년순대국밥",
      "rank": 3,
      "nickname": "취침",
      "job": "아크메이지(썬,콜)",
      "level": 106,
      "powerValue": 112242247120000,
      "powerText": "112조 2422억 4712만",
      "previousPowerValue": null,
      "previousPowerText": null,
      "powerGrowthValue": null,
      "powerGrowthText": null,
      "powerGrowthRate": null,
      "tobeolValue": 10935830000,
      "tobeolText": "109억 3583만",
      "previousTobeolValue": null,
      "previousTobeolText": null,
      "tobeolGrowthValue": null,
      "tobeolGrowthText": null,
      "tobeolGrowthRate": null
    },
    {
      "guild": "풍년순대국밥",
      "rank": 4,
      "nickname": "로라상",
      "job": "아크메이지(썬,콜)",
      "level": 107,
      "powerValue": 109581260390000,
      "powerText": "109조 5812억 6039만",
      "previousPowerValue": null,
      "previousPowerText": null,
      "powerGrowthValue": null,
      "powerGrowthText": null,
      "powerGrowthRate": null,
      "tobeolValue": 0,
      "tobeolText": "0",
      "previousTobeolValue": null,
      "previousTobeolText": null,
      "tobeolGrowthValue": null,
      "tobeolGrowthText": null,
      "tobeolGrowthRate": null
    },
    {
      "guild": "풍년순대국밥",
      "rank": 5,
      "nickname": "이지은선생님",
      "job": "섀도어",
      "level": 104,
      "powerValue": 81153494920000,
      "powerText": "81조 1534억 9492만",
      "previousPowerValue": null,
      "previousPowerText": null,
      "powerGrowthValue": null,
      "powerGrowthText": null,
      "powerGrowthRate": null,
      "tobeolValue": 0,
      "tobeolText": "0",
      "previousTobeolValue": null,
      "previousTobeolText": null,
      "tobeolGrowthValue": null,
      "tobeolGrowthText": null,
      "tobeolGrowthRate": null
    },
    {
      "guild": "풍년순대국밥",
      "rank": 6,
      "nickname": "히여리",
      "job": "섀도어",
      "level": 105,
      "powerValue": 77589739100000,
      "powerText": "77조 5897억 3910만",
      "previousPowerValue": null,
      "previousPowerText": null,
      "powerGrowthValue": null,
      "powerGrowthText": null,
      "powerGrowthRate": null,
      "tobeolValue": 0,
      "tobeolText": "0",
      "previousTobeolValue": null,
      "previousTobeolText": null,
      "tobeolGrowthValue": null,
      "tobeolGrowthText": null,
      "tobeolGrowthRate": null
    },
    {
      "guild": "풍년순대국밥",
      "rank": 7,
      "nickname": "뮤료",
      "job": "섀도어",
      "level": 104,
      "powerValue": 74334420030000,
      "powerText": "74조 3344억 2003만",
      "previousPowerValue": null,
      "previousPowerText": null,
      "powerGrowthValue": null,
      "powerGrowthText": null,
      "powerGrowthRate": null,
      "tobeolValue": 0,
      "tobeolText": "0",
      "previousTobeolValue": null,
      "previousTobeolText": null,
      "tobeolGrowthValue": null,
      "tobeolGrowthText": null,
      "tobeolGrowthRate": null
    },
    {
      "guild": "풍년순대국밥",
      "rank": 8,
      "nickname": "로먕",
      "job": "섀도어",
      "level": 106,
      "powerValue": 59091517410000,
      "powerText": "59조 915억 1741만",
      "previousPowerValue": null,
      "previousPowerText": null,
      "powerGrowthValue": null,
      "powerGrowthText": null,
      "powerGrowthRate": null,
      "tobeolValue": 12375220000,
      "tobeolText": "123억 7522만",
      "previousTobeolValue": null,
      "previousTobeolText": null,
      "tobeolGrowthValue": null,
      "tobeolGrowthText": null,
      "tobeolGrowthRate": null
    },
    {
      "guild": "풍년순대국밥",
      "rank": 9,
      "nickname": "늙은마",
      "job": "비숍",
      "level": 105,
      "powerValue": 57164637710000,
      "powerText": "57조 1646억 3771만",
      "previousPowerValue": null,
      "previousPowerText": null,
      "powerGrowthValue": null,
      "powerGrowthText": null,
      "powerGrowthRate": null,
      "tobeolValue": 0,
      "tobeolText": "0",
      "previousTobeolValue": null,
      "previousTobeolText": null,
      "tobeolGrowthValue": null,
      "tobeolGrowthText": null,
      "tobeolGrowthRate": null
    },
    {
      "guild": "풍년순대국밥",
      "rank": 10,
      "nickname": "피키별",
      "job": "섀도어",
      "level": 105,
      "powerValue": 56580301860000,
      "powerText": "56조 5803억 186만",
      "previousPowerValue": null,
      "previousPowerText": null,
      "powerGrowthValue": null,
      "powerGrowthText": null,
      "powerGrowthRate": null,
      "tobeolValue": 0,
      "tobeolText": "0",
      "previousTobeolValue": null,
      "previousTobeolText": null,
      "tobeolGrowthValue": null,
      "tobeolGrowthText": null,
      "tobeolGrowthRate": null
    },
    {
      "guild": "풍년순대국밥",
      "rank": 11,
      "nickname": "은디탁",
      "job": "히어로",
      "level": 106,
      "powerValue": 51484769590000,
      "powerText": "51조 4847억 6959만",
      "previousPowerValue": null,
      "previousPowerText": null,
      "powerGrowthValue": null,
      "powerGrowthText": null,
      "powerGrowthRate": null,
      "tobeolValue": 12624660000,
      "tobeolText": "126억 2466만",
      "previousTobeolValue": null,
      "previousTobeolText": null,
      "tobeolGrowthValue": null,
      "tobeolGrowthText": null,
      "tobeolGrowthRate": null
    },
    {
      "guild": "풍년순대국밥",
      "rank": 12,
      "nickname": "감성만땅보이",
      "job": "섀도어",
      "level": 104,
      "powerValue": 48819096910000,
      "powerText": "48조 8190억 9691만",
      "previousPowerValue": null,
      "previousPowerText": null,
      "powerGrowthValue": null,
      "powerGrowthText": null,
      "powerGrowthRate": null,
      "tobeolValue": 0,
      "tobeolText": "0",
      "previousTobeolValue": null,
      "previousTobeolText": null,
      "tobeolGrowthValue": null,
      "tobeolGrowthText": null,
      "tobeolGrowthRate": null
    },
    {
      "guild": "풍년순대국밥",
      "rank": 13,
      "nickname": "야제",
      "job": "섀도어",
      "level": 104,
      "powerValue": 47564878690000,
      "powerText": "47조 5648억 7869만",
      "previousPowerValue": null,
      "previousPowerText": null,
      "powerGrowthValue": null,
      "powerGrowthText": null,
      "powerGrowthRate": null,
      "tobeolValue": 10307220000,
      "tobeolText": "103억 722만",
      "previousTobeolValue": null,
      "previousTobeolText": null,
      "tobeolGrowthValue": null,
      "tobeolGrowthText": null,
      "tobeolGrowthRate": null
    },
    {
      "guild": "풍년순대국밥",
      "rank": 14,
      "nickname": "그냐앙",
      "job": "비숍",
      "level": 104,
      "powerValue": 44597466510000,
      "powerText": "44조 5974억 6651만",
      "previousPowerValue": null,
      "previousPowerText": null,
      "powerGrowthValue": null,
      "powerGrowthText": null,
      "powerGrowthRate": null,
      "tobeolValue": 8950990000,
      "tobeolText": "89억 5099만",
      "previousTobeolValue": null,
      "previousTobeolText": null,
      "tobeolGrowthValue": null,
      "tobeolGrowthText": null,
      "tobeolGrowthRate": null
    },
    {
      "guild": "풍년순대국밥",
      "rank": 15,
      "nickname": "부라",
      "job": "아크메이지(썬,콜)",
      "level": 104,
      "powerValue": 43556804620000,
      "powerText": "43조 5568억 462만",
      "previousPowerValue": null,
      "previousPowerText": null,
      "powerGrowthValue": null,
      "powerGrowthText": null,
      "powerGrowthRate": null,
      "tobeolValue": 8090110000,
      "tobeolText": "80억 9011만",
      "previousTobeolValue": null,
      "previousTobeolText": null,
      "tobeolGrowthValue": null,
      "tobeolGrowthText": null,
      "tobeolGrowthRate": null
    },
    {
      "guild": "풍년순대국밥",
      "rank": 16,
      "nickname": "이호은",
      "job": "섀도어",
      "level": 104,
      "powerValue": 42961961520000,
      "powerText": "42조 9619억 6152만",
      "previousPowerValue": null,
      "previousPowerText": null,
      "powerGrowthValue": null,
      "powerGrowthText": null,
      "powerGrowthRate": null,
      "tobeolValue": 0,
      "tobeolText": "0",
      "previousTobeolValue": null,
      "previousTobeolText": null,
      "tobeolGrowthValue": null,
      "tobeolGrowthText": null,
      "tobeolGrowthRate": null
    },
    {
      "guild": "풍년순대국밥",
      "rank": 17,
      "nickname": "근카자",
      "job": "섀도어",
      "level": 104,
      "powerValue": 40960814160000,
      "powerText": "40조 9608억 1416만",
      "previousPowerValue": null,
      "previousPowerText": null,
      "powerGrowthValue": null,
      "powerGrowthText": null,
      "powerGrowthRate": null,
      "tobeolValue": 0,
      "tobeolText": "0",
      "previousTobeolValue": null,
      "previousTobeolText": null,
      "tobeolGrowthValue": null,
      "tobeolGrowthText": null,
      "tobeolGrowthRate": null
    },
    {
      "guild": "풍년순대국밥",
      "rank": 18,
      "nickname": "네모수박",
      "job": "아크메이지(썬,콜)",
      "level": 105,
      "powerValue": 40747784760000,
      "powerText": "40조 7477억 8476만",
      "previousPowerValue": null,
      "previousPowerText": null,
      "powerGrowthValue": null,
      "powerGrowthText": null,
      "powerGrowthRate": null,
      "tobeolValue": 10244010000,
      "tobeolText": "102억 4401만",
      "previousTobeolValue": null,
      "previousTobeolText": null,
      "tobeolGrowthValue": null,
      "tobeolGrowthText": null,
      "tobeolGrowthRate": null
    },
    {
      "guild": "풍년순대국밥",
      "rank": 19,
      "nickname": "jinajina",
      "job": "아크메이지(썬,콜)",
      "level": 104,
      "powerValue": 40431133190000,
      "powerText": "40조 4311억 3319만",
      "previousPowerValue": null,
      "previousPowerText": null,
      "powerGrowthValue": null,
      "powerGrowthText": null,
      "powerGrowthRate": null,
      "tobeolValue": 0,
      "tobeolText": "0",
      "previousTobeolValue": null,
      "previousTobeolText": null,
      "tobeolGrowthValue": null,
      "tobeolGrowthText": null,
      "tobeolGrowthRate": null
    },
    {
      "guild": "풍년순대국밥",
      "rank": 20,
      "nickname": "혁혁",
      "job": "아크메이지(썬,콜)",
      "level": 103,
      "powerValue": 39531596950000,
      "powerText": "39조 5315억 9695만",
      "previousPowerValue": null,
      "previousPowerText": null,
      "powerGrowthValue": null,
      "powerGrowthText": null,
      "powerGrowthRate": null,
      "tobeolValue": 8412070000,
      "tobeolText": "84억 1207만",
      "previousTobeolValue": null,
      "previousTobeolText": null,
      "tobeolGrowthValue": null,
      "tobeolGrowthText": null,
      "tobeolGrowthRate": null
    },
    {
      "guild": "풍년순대국밥",
      "rank": 21,
      "nickname": "켠석",
      "job": "히어로",
      "level": 103,
      "powerValue": 30232958020000,
      "powerText": "30조 2329억 5802만",
      "previousPowerValue": null,
      "previousPowerText": null,
      "powerGrowthValue": null,
      "powerGrowthText": null,
      "powerGrowthRate": null,
      "tobeolValue": 0,
      "tobeolText": "0",
      "previousTobeolValue": null,
      "previousTobeolText": null,
      "tobeolGrowthValue": null,
      "tobeolGrowthText": null,
      "tobeolGrowthRate": null
    },
    {
      "guild": "풍년순대국밥",
      "rank": 22,
      "nickname": "애기이잉",
      "job": "아크메이지(썬,콜)",
      "level": 103,
      "powerValue": 28540606750000,
      "powerText": "28조 5406억 675만",
      "previousPowerValue": null,
      "previousPowerText": null,
      "powerGrowthValue": null,
      "powerGrowthText": null,
      "powerGrowthRate": null,
      "tobeolValue": 10038480000,
      "tobeolText": "100억 3848만",
      "previousTobeolValue": null,
      "previousTobeolText": null,
      "tobeolGrowthValue": null,
      "tobeolGrowthText": null,
      "tobeolGrowthRate": null
    },
    {
      "guild": "풍년순대국밥",
      "rank": 23,
      "nickname": "덕장이다습할",
      "job": "보우마스터",
      "level": 104,
      "powerValue": 26141554670000,
      "powerText": "26조 1415억 5467만",
      "previousPowerValue": null,
      "previousPowerText": null,
      "powerGrowthValue": null,
      "powerGrowthText": null,
      "powerGrowthRate": null,
      "tobeolValue": 0,
      "tobeolText": "0",
      "previousTobeolValue": null,
      "previousTobeolText": null,
      "tobeolGrowthValue": null,
      "tobeolGrowthText": null,
      "tobeolGrowthRate": null
    },
    {
      "guild": "풍년순대국밥",
      "rank": 24,
      "nickname": "24YB",
      "job": "신궁",
      "level": 104,
      "powerValue": 26027338210000,
      "powerText": "26조 273억 3821만",
      "previousPowerValue": null,
      "previousPowerText": null,
      "powerGrowthValue": null,
      "powerGrowthText": null,
      "powerGrowthRate": null,
      "tobeolValue": 0,
      "tobeolText": "0",
      "previousTobeolValue": null,
      "previousTobeolText": null,
      "tobeolGrowthValue": null,
      "tobeolGrowthText": null,
      "tobeolGrowthRate": null
    },
    {
      "guild": "풍년순대국밥",
      "rank": 25,
      "nickname": "믄지",
      "job": "보우마스터",
      "level": 103,
      "powerValue": 16976290290000,
      "powerText": "16조 9762억 9029만",
      "previousPowerValue": null,
      "previousPowerText": null,
      "powerGrowthValue": null,
      "powerGrowthText": null,
      "powerGrowthRate": null,
      "tobeolValue": 0,
      "tobeolText": "0",
      "previousTobeolValue": null,
      "previousTobeolText": null,
      "tobeolGrowthValue": null,
      "tobeolGrowthText": null,
      "tobeolGrowthRate": null
    },
    {
      "guild": "풍년순대국밥",
      "rank": 26,
      "nickname": "다크날동",
      "job": "다크나이트",
      "level": 78,
      "powerValue": 1678740000,
      "powerText": "16억 7874만",
      "previousPowerValue": null,
      "previousPowerText": null,
      "powerGrowthValue": null,
      "powerGrowthText": null,
      "powerGrowthRate": null,
      "tobeolValue": 0,
      "tobeolText": "0",
      "previousTobeolValue": null,
      "previousTobeolText": null,
      "tobeolGrowthValue": null,
      "tobeolGrowthText": null,
      "tobeolGrowthRate": null
    }
  ]
}
